login_activity/__init__.py
login_activity/admin.py
login_activity/apps.py
login_activity/cli.py
login_activity/models.py
login_activity/signals.py
login_activity/tests.py
login_activity/urls.py
login_activity/views.py
login_activity/migrations/__init__.py
django_login_activity-0.1.3.dist-info/METADATA
django_login_activity-0.1.3.dist-info/WHEEL
django_login_activity-0.1.3.dist-info/entry_points.txt
django_login_activity-0.1.3.dist-info/top_level.txt
django_login_activity-0.1.3.dist-info/RECORD
